bluelight_license_info.py
bluelight_license_info-0.1.0.dist-info/METADATA
bluelight_license_info-0.1.0.dist-info/WHEEL
bluelight_license_info-0.1.0.dist-info/entry_points.txt
bluelight_license_info-0.1.0.dist-info/top_level.txt
bluelight_license_info-0.1.0.dist-info/RECORD
