Metadata-Version: 2.4
Name: bluelight-license-info
Version: 0.1.0
Summary: Shows license info for BluelightAI software.
Author-email: BluelightAI <hello@bluelightai.com>
Requires-Python: >=3.8
Requires-Dist: cryptography
Requires-Dist: requests
